infernosaurus/__init__.py
infernosaurus/const.py
infernosaurus/inference_backend_base.py
infernosaurus/inference_operator.py
infernosaurus/models.py
infernosaurus/typing.py
infernosaurus/utils.py
infernosaurus/backends/__init__.py
infernosaurus/backends/llama_cpp/__init__.py
infernosaurus/backends/llama_cpp/backend.py
infernosaurus/backends/llama_cpp/bootstrap_server.py
infernosaurus/backends/llama_cpp/scripts/main_job.py
infernosaurus/backends/llama_cpp/scripts/worker_job.py
tests/conftest.py
tests/test_llama_cpp.py
infernosaurus-0.4.0.dist-info/METADATA
infernosaurus-0.4.0.dist-info/WHEEL
infernosaurus-0.4.0.dist-info/top_level.txt
infernosaurus-0.4.0.dist-info/RECORD
